micofam/__init__.py
micofam/micofam_db.py
micofam/micofam_main.py
micofam/micofam_plugin.py
micofam/res/dNmax.txt
micofam/res/icon.png
micofam/res/rve_dialog.png
micofam/user/lin_elastic - backup.for
micofam/user/lin_elastic.for
micofam/user/visco_poynting_eulerfwd.for
micofam-1.1.0.dist-info/LICENSE
micofam-1.1.0.dist-info/METADATA
micofam-1.1.0.dist-info/WHEEL
micofam-1.1.0.dist-info/entry_points.txt
micofam-1.1.0.dist-info/RECORD
