Metadata-Version: 2.1
Name: micofam
Version: 1.1.0
Summary: Micromechanical Composite Fatigue Modeler
Home-page: https://gitlab.com/dlr-sy/micofam
License: MIT
Keywords: analysis,micromechanics,rve
Author: Krause, Daniel
Author-email: daniel.krause@dlr.de
Maintainer: Garbade, Marc
Maintainer-email: marc.garbade@dlr.de
Requires-Python: >=2.7, !=3.0.*, !=3.1.*, !=3.2.*, !=3.3.*, !=3.4.*
Classifier: Development Status :: 7 - Inactive
Classifier: License :: OSI Approved :: MIT License
Classifier: Operating System :: OS Independent
Classifier: Programming Language :: Python :: 2
Classifier: Programming Language :: Python :: 2.7
Classifier: Programming Language :: Python :: 3
Classifier: Programming Language :: Python :: 3.5
Classifier: Programming Language :: Python :: 3.6
Classifier: Programming Language :: Python :: 3.7
Classifier: Programming Language :: Python :: 3.8
Classifier: Programming Language :: Python :: 3.9
Classifier: Programming Language :: Python :: 3.10
Classifier: Programming Language :: Python :: 3.11
Classifier: Topic :: Scientific/Engineering
Requires-Dist: importlib-metadata (<2.0) ; python_version >= "2.7" and python_version < "2.8" or python_version >= "3.5" and python_version < "3.7"
Requires-Dist: importlib-metadata (>=4.0) ; python_version >= "3.7" and python_version < "4.0"
Requires-Dist: typer (>=0.12) ; python_version >= "3.7" and python_version < "4.0"
Project-URL: Repository, https://gitlab.com/dlr-sy/micofam
